LICENSE
MANIFEST.in
README.rst
setup.py
oauth_flow/__init__.py
oauth_flow.egg-info/PKG-INFO
oauth_flow.egg-info/SOURCES.txt
oauth_flow.egg-info/dependency_links.txt
oauth_flow.egg-info/requires.txt
oauth_flow.egg-info/top_level.txt
oauth_flow/handlers/__init__.py
oauth_flow/handlers/facebook.py
oauth_flow/handlers/google.py
oauth_flow/handlers/twitter.py
oauth_flow/handlers/yahoo.py
oauth_flow/utils/__init__.py
oauth_flow/utils/anytree.py